goto/__init__.py
goto/settings.py
goto/the_real_goto.py
goto/commands/__init__.py
goto/commands/add.py
goto/commands/check_migrate.py
goto/commands/commands.py
goto/commands/default.py
goto/commands/help.py
goto/commands/list.py
goto/commands/migrate.py
goto/commands/rename.py
goto/commands/rm.py
goto/commands/show.py
goto/commands/update.py
goto/gotomagic/__init__.py
goto/gotomagic/git.py
goto/gotomagic/magic.py
goto/gotomagic/utils.py
goto/gotomagic/text/__init__.py
goto/gotomagic/text/error.py
goto/gotomagic/text/text.py
goto/gotomagic/text/warning.py
goto/plugins/__init__.py
goto/plugins/copy.py
goto/plugins/intellij.py
goto/plugins/open.py
goto/plugins/rider.py
goto/plugins/subl.py
goto/plugins/vscode.py
goto/tests/__init__.py
goto/tests/test_gotomagic.py
goto/tests/test_text.py
magicgoto-1.6.2.data/scripts/_gotoutils
magicgoto-1.6.2.data/scripts/goto
magicgoto-1.6.2.data/scripts/install_goto
magicgoto-1.6.2.data/scripts/project
magicgoto-1.6.2.data/scripts/start_goto
magicgoto-1.6.2.dist-info/LICENSE
magicgoto-1.6.2.dist-info/METADATA
magicgoto-1.6.2.dist-info/WHEEL
magicgoto-1.6.2.dist-info/entry_points.txt
magicgoto-1.6.2.dist-info/top_level.txt
magicgoto-1.6.2.dist-info/RECORD
