Metadata-Version: 2.1
Name: magicgoto
Version: 1.6.2
Summary: Magic goto - goto where you need to be, right now.
Home-page: https://gotogoto.ninja
Author: Robin Aaberg
Author-email: robin.garen@gmail.com
License: UNKNOWN
Platform: UNKNOWN
Classifier: Programming Language :: Python :: 3
Classifier: License :: OSI Approved :: MIT License
Classifier: Operating System :: OS Independent
Requires-Python: >=3.3
Requires-Dist: pyperclip
Requires-Dist: gitpython
Requires-Dist: future
